{"objectId":"129602","ipfsHash":"QmZdxp14rfj7MD7Nz392iMjdMJSQQqGVXYa2euFUn4Y9WR","token_id":"129602","total_amount":25,"token_info":{"name":"SPACE KNOT","description":"SPACE KNOT is a generative animation built in javascript with Hydra. Click for sound. Move your mouse to introduce faux chromatic aberration. You can find printed space knots in my print shop: dnlsmm.studio/ | twitter.com/dnlsmm | instagram.com/dnlsmm.studio","tags":["GENERATIVE","ANIMATION","INTERACTIVE","CODING","CREATIVECODING","CODEART","SPACE","IMMERSIVE","SOUNDSCAPE","TEXTURE","NOISE","JAVASCRIPT","HYDRA"],"symbol":"OBJKT","artifactUri":"ipfs://QmSqfrscfTzCGdnzKMLpV9cKinUud92KL2eRYeoMSdon4G","displayUri":"ipfs://QmTuUixWUfJWobbNevGYweJy7WnSA4Db3JLcBYMwcCRJLe","thumbnailUri":"ipfs://QmSktbsBXMTF5Xt13F7SXvEDATb1gGuMp6MD9mZSRLuRux","creators":["tz1hY7NtouMvSXJxhK3vbr7o99aQwmzkawgf"],"formats":[{"uri":"ipfs://QmSqfrscfTzCGdnzKMLpV9cKinUud92KL2eRYeoMSdon4G","mimeType":"application/x-directory"}],"decimals":0,"isBooleanAmount":false,"shouldPreferSymbol":false}}