{"objectId":"30498","ipfsHash":"QmPhmT7KXiKh7w8c4VQzrFQss44kHHzw8TReD7yWBjXYYz","token_id":"30498","total_amount":1,"token_info":{"name":"PHYSICAL STOCK PHOTO #3","description":"Images are rarely complete or true. Information and attribution can be added, replicated and deleted. Issues of trust and authenticity arise. Feelings of confusion and dislocation are normal. The original sometimes completely disappears. This object is a public domain stock photo of a landscape, fed incorrectly through Rhino 3D with accidental processes. It can be physically produced. The owner can contact info@crashblossom.co for a file optimised for physical 3D production.","tags":["3D","3Dmodel","glb","sculpture","3Dprintable","abstract","metal"],"symbol":"OBJKT","artifactUri":"ipfs://QmNrKrosiXsscdpQyuxnA7Eg3n5gtcVjCWvesZZR8T7Bbi","displayUri":"","thumbnailUri":"ipfs://QmNrhZHUaEqxhyLfqoq1mtHSipkWHeT31LNHb1QEbDHgnc","creators":["tz1fzJFDVUYJSCv5EkXWv6S1zDNjmPtsxRD2"],"formats":[{"uri":"ipfs://QmNrKrosiXsscdpQyuxnA7Eg3n5gtcVjCWvesZZR8T7Bbi","mimeType":"model/gltf-binary"}],"decimals":0,"isBooleanAmount":false,"shouldPreferSymbol":false}}