{"objectId":"59415","ipfsHash":"QmRVgZNnNMTxRc9xoqpmHLn38W22GRaQn8f6cKWFXFKJhw","token_id":"59415","total_amount":21,"token_info":{"name":"Changes [var. 01]","description":"Part 1 of 3, fast. Imagine this projected to your wall. Watch fullscreen! Generative artwork by LIA (www.liaworks.com), 2021. Edition of 20 + 1 AP","tags":["LIA","generativeart","generative","abstract","abstractart","creativecoding","softwareart","codeart","algorithm","algorithmicart","mathart","creativecodeart","madewithcode","computationalart","colors"],"symbol":"OBJKT","artifactUri":"ipfs://QmSFB6jwuFch57WsqJUpqtWurMBbYGWTfGPfPxkwcAk1GP","displayUri":"ipfs://QmWhmQo6bRzZGX8mqasrsWye7f3URSMnPfVnmZofTKCVJZ","thumbnailUri":"ipfs://QmNrhZHUaEqxhyLfqoq1mtHSipkWHeT31LNHb1QEbDHgnc","creators":["tz1auPyXVaMy3GntdCQwH2VGNuFj6bAocj2v"],"formats":[{"uri":"ipfs://QmSFB6jwuFch57WsqJUpqtWurMBbYGWTfGPfPxkwcAk1GP","mimeType":"application/x-directory"}],"decimals":0,"isBooleanAmount":false,"shouldPreferSymbol":false}}