{"objectId":"75770","ipfsHash":"QmSmNF1H9z5tLfbterXu71am3m1VJyzsNgPqveh8rbGjDz","token_id":"75770","total_amount":100,"token_info":{"name":"AMOLED","description":"I love colors and motion, and long time ago I creaded AMOLED. I used this engine in my Live Wallpaper for phones. Milion users download phone version of AMOLED.  You can download it too, for free, from Google Play Store. Best for amoled displays. Now I created NFT version of AMOLED. It's 3D, interactive (move mouse) and fun. | Made by MAXELUS | @maxelusNet","tags":["colors","interactive","cleanNFT","generativeart","particle","webgl","maxelusNet","maxelus"],"symbol":"OBJKT","artifactUri":"ipfs://QmX6S9TcPtzKXL5C3zgPrHzQ2u5XnNv2JWJ1nEuxtPy589","displayUri":"ipfs://QmWW8tHaH3Vm1HVU7nbeBW734VyVbjXAeYMNKs6e1CWvXC","thumbnailUri":"ipfs://QmNrhZHUaEqxhyLfqoq1mtHSipkWHeT31LNHb1QEbDHgnc","creators":["tz1WJ9dTwb1qFj4sEZSXtABXZgXaRURgCjep"],"formats":[{"uri":"ipfs://QmX6S9TcPtzKXL5C3zgPrHzQ2u5XnNv2JWJ1nEuxtPy589","mimeType":"application/x-directory"}],"decimals":0,"isBooleanAmount":false,"shouldPreferSymbol":false}}