{"objectId":"83206","ipfsHash":"QmcH8uULTYdaR2BoS1tJZ4amGX4GU6aLh66fRfkQgPRggY","token_id":"83206","total_amount":100,"token_info":{"name":"BETTA FISH | 2-8 | INTERACTIVE : CLICK MOUSE","description":"BETTA FISH is 3D realtime fish. Interactive : You can touch fish > CLICK mouse. You can get phone version (Live Wallpaper) from Google Play. Made by MAXELUS | TW: @maxelusNET | #interactive #webgl #betta #maxelus","tags":["interactive","betta","bettafish","webgl","maxelusNet","maxelus"],"symbol":"OBJKT","artifactUri":"ipfs://QmSg7TBPVkYgAd7NjjAtBhZfvHv3r3KSXik62sPKcMoPKR","displayUri":"ipfs://QmbRrabPjzcYnZmUrAELQ9P2aVUx6tXB5nimTJ6CputUQn","thumbnailUri":"ipfs://QmNrhZHUaEqxhyLfqoq1mtHSipkWHeT31LNHb1QEbDHgnc","creators":["tz1WJ9dTwb1qFj4sEZSXtABXZgXaRURgCjep"],"formats":[{"uri":"ipfs://QmSg7TBPVkYgAd7NjjAtBhZfvHv3r3KSXik62sPKcMoPKR","mimeType":"application/x-directory"}],"decimals":0,"isBooleanAmount":false,"shouldPreferSymbol":false}}