{"objectId":"83475","ipfsHash":"QmaC2bLzEtWAGA3pbLjzJ7mj1tuNjcAyuWFDmL4VhGUoW1","token_id":"83475","total_amount":5,"token_info":{"name":"Synth Monsters 3D - 006 - Mosemo (Gold)","description":"Mosemo is an Ice type Monster that tends to be naturally shy, it spends it's days hunting through snow drifts for acorns to eat. Epic rarity Gold edition - only 5 can be caught.","tags":["nft","monster","synth"],"symbol":"OBJKT","artifactUri":"ipfs://QmSh2LUtK8xN9XyKGpd2NQ8REfzSjbXAboPE4gdqrumew1","displayUri":"","thumbnailUri":"ipfs://QmNrhZHUaEqxhyLfqoq1mtHSipkWHeT31LNHb1QEbDHgnc","creators":["tz1fHYPVfTSXUZ4tFqUweAjwhUmPJuZiNcfv"],"formats":[{"uri":"ipfs://QmSh2LUtK8xN9XyKGpd2NQ8REfzSjbXAboPE4gdqrumew1","mimeType":"model/gltf-binary"}],"decimals":0,"isBooleanAmount":false,"shouldPreferSymbol":false}}