{"objectId":"87933","ipfsHash":"QmZ22BLG6B5JqNDUXTmiHcuM65EEtrVPECrwagmvp9Qj5J","token_id":"87933","total_amount":1,"token_info":{"name":"trashy heart #8","description":"3D object and animation based on a tattoo sketch / collector can use the piece for a tattoo motive itself","tags":["art","abstract","nft","nftart","nftartist","3d","3dart","heart","love"],"symbol":"OBJKT","artifactUri":"ipfs://QmVBGz8BBPSPFG4tZwoViLosuA3GxzaftELzxvMSg6dyAP","displayUri":"","thumbnailUri":"ipfs://QmNrhZHUaEqxhyLfqoq1mtHSipkWHeT31LNHb1QEbDHgnc","creators":["tz1Vn6isG5Y5pudW3ZzFqpGT8gAiDNzZPvns"],"formats":[{"uri":"ipfs://QmVBGz8BBPSPFG4tZwoViLosuA3GxzaftELzxvMSg6dyAP","mimeType":"model/gltf-binary"}],"decimals":0,"isBooleanAmount":false,"shouldPreferSymbol":false}}