{"objectId":"91710","ipfsHash":"QmcLwdLbC3aJYcGYVQ4nCKPDfqvUNuJestHNKmUaEzep2p","token_id":"91710","total_amount":20,"token_info":{"name":"Turtles all the Way Down (after Edward Kemeys after Constantin Brâncuși)","description":"Artwork for the #hicathon event. An Edward Kemeys lion that guards the entrance to the Art Institute of Chicago reimagined as a modular structure channeling Constantin Brâncuși. This 3D object was originally produced in 2013 and physical versions of it have been exhibited widely in the USA and beyond. THis is the first time it has been shown in this fashion. https://en.wikipedia.org/wiki/Turtles_all_the_way_down ","tags":["hicathon","hicetnunc","cleannft","EdwardKemeys","ConstantinBrâncuși","ArtInstituteofChicago","nut","bolt","thread","modular","TomBurtonwood"],"symbol":"OBJKT","artifactUri":"ipfs://QmSTuF7GwprmnB7hXUJXNo8yjXndK5HfUNsxmUgcFAgnWi","displayUri":"","thumbnailUri":"ipfs://QmNrhZHUaEqxhyLfqoq1mtHSipkWHeT31LNHb1QEbDHgnc","creators":["tz1MD4pRPwoh3RadNT1fj3rpUqTAa9X2xim9"],"formats":[{"uri":"ipfs://QmSTuF7GwprmnB7hXUJXNo8yjXndK5HfUNsxmUgcFAgnWi","mimeType":"model/gltf-binary"}],"decimals":0,"isBooleanAmount":false,"shouldPreferSymbol":false}}